cfapyx/__init__.py
cfapyx/backend.py
cfapyx/creator.py
cfapyx/datastore.py
cfapyx/decoder.py
cfapyx/group.py
cfapyx/tests/__init__.py
cfapyx/tests/conftest.py
cfapyx/tests/test_basic.py
cfapyx/tests/test_read.py
cfapyx/tests/test_space/rain/example0.nc
cfapyx/tests/test_space/rain/example1.nc
cfapyx/tests/test_space/rain/example2.nc
cfapyx/tests/test_space/rain/example3.nc
cfapyx/tests/test_space/rain/example4.nc
cfapyx/tests/test_space/rain/example5.nc
cfapyx/tests/test_space/rain/example6.nc
cfapyx/tests/test_space/rain/example7.nc
cfapyx/tests/test_space/rain/example8.nc
cfapyx/tests/test_space/rain/example9.nc
cfapyx/tests/test_space/rain/rainmaker.nca
cfapyx/tests/test_space/test_outputs/testrain.nca
cfapyx/tests/test_space/testrain.nca
cfapyx/tests/test_write.py
cfapyx/utils.py
cfapyx/wrappers.py
cfapyx-2025.12.9.dist-info/LICENSE
cfapyx-2025.12.9.dist-info/METADATA
cfapyx-2025.12.9.dist-info/WHEEL
cfapyx-2025.12.9.dist-info/entry_points.txt
cfapyx-2025.12.9.dist-info/RECORD
