Metadata-Version: 2.3
Name: cfapyx
Version: 2025.12.9
Summary: The pure-Python implementation of the CF Aggregation conventions, including the Xarray engine to enable reading CFA-netCDF files.
License: BSD 3
Author: Daniel Westwood
Author-email: daniel.westwood@stfc.ac.uk
Requires-Python: >=3.11,<4.0
Classifier: License :: Other/Proprietary License
Classifier: Programming Language :: Python :: 3
Classifier: Programming Language :: Python :: 3.11
Classifier: Programming Language :: Python :: 3.12
Classifier: Programming Language :: Python :: 3.13
Requires-Dist: arraypartition (>=1.2.0)
Requires-Dist: dask (>=2025.3.0)
Requires-Dist: netCDF4 (>=1.7.2)
Requires-Dist: numpy (>=2.0.0)
Requires-Dist: xarray (>=2025.11.0)
